beam_io_utils/__init__.py
beam_io_utils/transforms.py
beam_io_utils/transforms_test.py
beam_io_utils/xcsv.py
beam_io_utils/xcsv_test.py
beam_io_utils/xjson.py
beam_io_utils/xjson_test.py
beam_io_utils-0.0.7.dist-info/LICENSE.md
beam_io_utils-0.0.7.dist-info/METADATA
beam_io_utils-0.0.7.dist-info/WHEEL
beam_io_utils-0.0.7.dist-info/top_level.txt
beam_io_utils-0.0.7.dist-info/RECORD
