Metadata-Version: 2.1
Name: beam-io-utils
Version: 0.0.7
Summary: Utilities for Apache Beam disk io (local or on GCP)
Home-page: https://github.com/raywhite/beam-io-utils
Author: axdg
Author-email: axdg@dfant.asia
License: UNLICENSED
Keywords: apache beam dataflow google cloud platform
Platform: UNKNOWN
Requires-Python: >=2.6,<=3.0
Requires-Dist: apache-beam[gcp]
